hyperquant/__init__.py
hyperquant/core.py
hyperquant/db.py
hyperquant/draw.py
hyperquant/logkit.py
hyperquant/notikit.py
hyperquant/broker/auth.py
hyperquant/broker/bitget.py
hyperquant/broker/bitmart.py
hyperquant/broker/coinw.py
hyperquant/broker/deepcoin.py
hyperquant/broker/edgex.py
hyperquant/broker/hyperliquid.py
hyperquant/broker/lbank.py
hyperquant/broker/lighter.py
hyperquant/broker/ourbit.py
hyperquant/broker/polymarket.py
hyperquant/broker/ws.py
hyperquant/broker/lib/edgex_sign.py
hyperquant/broker/lib/hpstore.py
hyperquant/broker/lib/hyper_types.py
hyperquant/broker/lib/util.py
hyperquant/broker/lib/polymarket/ctfAbi.py
hyperquant/broker/lib/polymarket/safeAbi.py
hyperquant/broker/models/apexpro.py
hyperquant/broker/models/bitget.py
hyperquant/broker/models/bitmart.py
hyperquant/broker/models/coinw.py
hyperquant/broker/models/deepcoin.py
hyperquant/broker/models/edgex.py
hyperquant/broker/models/hyperliquid.py
hyperquant/broker/models/lbank.py
hyperquant/broker/models/lighter.py
hyperquant/broker/models/ourbit.py
hyperquant/broker/models/polymarket.py
hyperquant/datavison/_util.py
hyperquant/datavison/binance.py
hyperquant/datavison/coinglass.py
hyperquant/datavison/okx.py
hyperquant-1.49.dist-info/METADATA
hyperquant-1.49.dist-info/WHEEL
hyperquant-1.49.dist-info/RECORD
